houdini_mcp/__init__.py
houdini_mcp/main.py
houdini_mcp/server.py
houdini_mcp-0.1.0.dist-info/METADATA
houdini_mcp-0.1.0.dist-info/WHEEL
houdini_mcp-0.1.0.dist-info/entry_points.txt
houdini_mcp-0.1.0.dist-info/top_level.txt
houdini_mcp-0.1.0.dist-info/RECORD
