Metadata-Version: 2.4
Name: houdini-mcp
Version: 0.1.0
Summary: Houdini integration through the Model Context Protocol
Author-email: capoom <merih@capoom.com>
License: MIT
Project-URL: Homepage, https://github.com/yourusername/houdini-mcp
Project-URL: Bug Tracker, https://github.com/yourusername/houdini-mcp/issues
Classifier: Programming Language :: Python :: 3
Classifier: License :: OSI Approved :: MIT License
Classifier: Operating System :: OS Independent
Requires-Python: >=3.9.0
